metropolis/__init__.py
metropolis/core.py
metropolis/energies.py
metropolis/main.py
metropolis/schedule.py
metropolis/visualization.py
metropolis_sa-5.0.0.dist-info/licenses/LICENSE
metropolis_sa-5.0.0.dist-info/METADATA
metropolis_sa-5.0.0.dist-info/WHEEL
metropolis_sa-5.0.0.dist-info/entry_points.txt
metropolis_sa-5.0.0.dist-info/top_level.txt
metropolis_sa-5.0.0.dist-info/RECORD
