Metadata-Version: 2.4
Name: metropolis-SA
Version: 5.0.0
Summary: Simulated Annealing with Metropolis algorithm w/ convergence tracking.
Author-email: "Jose M. Lopez" <chema.electronica@gmail.com>
License: MIT License
Project-URL: Homepage, https://github.com/chema-e/metropolis
Project-URL: Repository, https://github.com/chema-e/metropolis
Project-URL: Issues, https://github.com/chema-e/metropolis/issues
Requires-Python: >=3.8
License-File: LICENSE
Requires-Dist: numpy
Requires-Dist: matplotlib
Dynamic: license-file
